numba_mpi/__init__.py
numba_mpi/common.py
numba_mpi/utils.py
numba_mpi/api/__init__.py
numba_mpi/api/allreduce.py
numba_mpi/api/barrier.py
numba_mpi/api/bcast.py
numba_mpi/api/initialized.py
numba_mpi/api/irecv.py
numba_mpi/api/isend.py
numba_mpi/api/operator.py
numba_mpi/api/query_thread.py
numba_mpi/api/rank.py
numba_mpi/api/recv.py
numba_mpi/api/reduce.py
numba_mpi/api/requests.py
numba_mpi/api/scatter_gather.py
numba_mpi/api/send.py
numba_mpi/api/size.py
numba_mpi/api/wtime.py
numba_mpi-1.1.7.dist-info/licenses/LICENSE
numba_mpi-1.1.7.dist-info/METADATA
numba_mpi-1.1.7.dist-info/WHEEL
numba_mpi-1.1.7.dist-info/top_level.txt
numba_mpi-1.1.7.dist-info/RECORD
