Metadata-Version: 2.4
Name: numba-mpi
Version: 1.1.7
Summary: Numba @jittable MPI wrappers tested on Linux, macOS and Windows
Author-email: "https://github.com/numba-mpi/numba-mpi/graphs/contributors" <sylwester.arabas@agh.edu.pl>
License-Expression: GPL-3.0-only
Project-URL: Tracker, https://github.com/numba-mpi/numba-mpi/issues
Project-URL: Documentation, https://numba-mpi.github.io/numba-mpi
Project-URL: Source, https://github.com/numba-mpi/numba-mpi
Keywords: MPI,numba
Classifier: Development Status :: 4 - Beta
Classifier: Intended Audience :: Science/Research
Classifier: Operating System :: OS Independent
Classifier: Programming Language :: Python :: 3
Classifier: Topic :: Scientific/Engineering
Classifier: Topic :: Scientific/Engineering :: Mathematics
Classifier: Topic :: Scientific/Engineering :: Physics
Classifier: Topic :: Software Development :: Libraries
Requires-Python: >=3.8
License-File: LICENSE
Requires-Dist: numba
Requires-Dist: numpy
Requires-Dist: mpi4py
Requires-Dist: psutil
Provides-Extra: tests
Requires-Dist: pytest; extra == "tests"
Requires-Dist: py-pde; extra == "tests"
Provides-Extra: ci-version-pins
Requires-Dist: pytest==9.0.1; extra == "ci-version-pins"
Dynamic: license-file
